{
  "tasks": [
    {
      "status": "Completed",
      "id": 1,
      "description": "Library for JS application state management",
      "title": "Learn Redux"
    },
    {
      "status": "Unstarted",
      "description": "Math programming",
      "title": "Learn Python",
      "id": 3
    },
    {
      "title": "Learn Haskell",
      "description": "Functional programming",
      "id": 2,
      "status": "Unstarted"
    },
    {
      "title": "Learn Ramda",
      "description": "Functional Javascript in JS like Haskell",
      "status": "Completed",
      "id": 4
    },
    {
      "title": "Learn Rx",
      "description": "Observables",
      "status": "In Progress",
      "id": 5
    }
  ]
}